setup.py
yellow/__init__.py
yellow/yellow.py
yellow_sdk.egg-info/PKG-INFO
yellow_sdk.egg-info/SOURCES.txt
yellow_sdk.egg-info/dependency_links.txt
yellow_sdk.egg-info/not-zip-safe
yellow_sdk.egg-info/pbr.json
yellow_sdk.egg-info/requires.txt
yellow_sdk.egg-info/top_level.txt