Metadata-Version: 1.0
Name: yellow-sdk
Version: 0.2.3
Summary: Yellow Python SDK. A python module to easily integrate with the Yellow bitcoin payments API.
Home-page: http://yellowpay.co
Author: Eslam A. Hefnawy
Author-email: eslam@yellowpay.co
License: MIT
Platform: UNKNOWN
